stack.py
stackDfg.py
tkinter_vote.py
stackDfg-1.0.0.dist-info/DESCRIPTION.rst
stackDfg-1.0.0.dist-info/METADATA
stackDfg-1.0.0.dist-info/RECORD
stackDfg-1.0.0.dist-info/WHEEL
stackDfg-1.0.0.dist-info/metadata.json
stackDfg-1.0.0.dist-info/top_level.txt
