Metadata-Version: 2.0
Name: stackDfg
Version: 1.0.0
Summary: Stack class&module
Home-page: http://user.qzone.qq.com/306467355/2
Author: 董付国
Author-email: dongfuguo2005@126.com
License: UNKNOWN
Keywords: stack Python Python_dfg
Platform: UNKNOWN
